guiscrcpy/__init__.py
guiscrcpy/__main__.py
guiscrcpy/cli.py
guiscrcpy/constants.py
guiscrcpy/install/__init__.py
guiscrcpy/install/finder.py
guiscrcpy/launcher.py
guiscrcpy/lib/__init__.py
guiscrcpy/lib/bridge/__init__.py
guiscrcpy/lib/bridge/adb.py
guiscrcpy/lib/bridge/audio/__init__.py
guiscrcpy/lib/bridge/audio/base.py
guiscrcpy/lib/bridge/audio/sndcpy.py
guiscrcpy/lib/bridge/audio/usbaudio.py
guiscrcpy/lib/bridge/base.py
guiscrcpy/lib/bridge/exceptions.py
guiscrcpy/lib/bridge/scrcpy.py
guiscrcpy/lib/check.py
guiscrcpy/lib/config.py
guiscrcpy/lib/mapper/__init__.py
guiscrcpy/lib/mapper/mapper.py
guiscrcpy/lib/mapper/ux.py
guiscrcpy/lib/process.py
guiscrcpy/lib/toolkit.py
guiscrcpy/lib/utils.py
guiscrcpy/logging.py
guiscrcpy/network/__init__.py
guiscrcpy/network/network.py
guiscrcpy/platform/__init__.py
guiscrcpy/platform/darwin.py
guiscrcpy/platform/linux.py
guiscrcpy/platform/platform.py
guiscrcpy/platform/windows.py
guiscrcpy/platform/windows_tools/__init__.py
guiscrcpy/platform/windows_tools/shortcut.py
guiscrcpy/platform/windows_tools/tools.py
guiscrcpy/settings/__init__.py
guiscrcpy/settings/settings.py
guiscrcpy/theme/__init__.py
guiscrcpy/theme/decorate.py
guiscrcpy/theme/desktop_shortcut.py
guiscrcpy/theme/linux_desktop_shortcut_template.py
guiscrcpy/theme/style.py
guiscrcpy/theme/termcolor.py
guiscrcpy/ts/eng-eng.ts
guiscrcpy/ts/eng-es.ts
guiscrcpy/ts/eng-fr.ts
guiscrcpy/ts/template.ts
guiscrcpy/ui/__init__.py
guiscrcpy/ui/bottompanelui.ui
guiscrcpy/ui/downloader.ui
guiscrcpy/ui/fonts/NotoSans-Bold.ttf
guiscrcpy/ui/fonts/NotoSans-BoldItalic.ttf
guiscrcpy/ui/fonts/NotoSans-Italic.ttf
guiscrcpy/ui/fonts/NotoSans-Regular.ttf
guiscrcpy/ui/fonts/TitilliumWeb-Bold.ttf
guiscrcpy/ui/fonts/TitilliumWeb-Regular.ttf
guiscrcpy/ui/icons/android.svg
guiscrcpy/ui/icons/bell-musical-tool(2).svg
guiscrcpy/ui/icons/bell-musical-tool.svg
guiscrcpy/ui/icons/bullseye.svg
guiscrcpy/ui/icons/chevron-sign-down.svg
guiscrcpy/ui/icons/chevron-sign-left.svg
guiscrcpy-2023.1.1.dist-info/entry_points.txt
guiscrcpy-2023.1.1.dist-info/METADATA
guiscrcpy-2023.1.1.dist-info/LICENSE
guiscrcpy-2023.1.1.dist-info/WHEEL
guiscrcpy-2023.1.1.dist-info/RECORD
